demathpy/__init__.py
demathpy/ode.py
demathpy/pde.py
demathpy/symbols.py
demathpy-0.1.0.dist-info/licenses/LICENSE
demathpy-0.1.0.dist-info/WHEEL
demathpy-0.1.0.dist-info/METADATA
demathpy-0.1.0.dist-info/RECORD
