Metadata-Version: 2.4
Name: demathpy
Version: 0.1.0
Summary: PDE/ODE math backend
Author: Misekai
Author-email: Misekai <mcore-us@misekai.net>
License-Expression: MIT
License-File: LICENSE
Requires-Dist: numpy>=1.24.0
Requires-Dist: sympy>=1.12.0
Requires-Dist: typing>=3.10.0.0
Requires-Python: >=3.10
